CONTRIBUTORS
LICENSE.txt
MANIFEST.in
README.rst
setup.py
django_laporem_field.egg-info/PKG-INFO
django_laporem_field.egg-info/SOURCES.txt
django_laporem_field.egg-info/dependency_links.txt
django_laporem_field.egg-info/requires.txt
django_laporem_field.egg-info/top_level.txt
laporem_field/__init__.py
laporem_field/admin.py
laporem_field/forms.py
laporem_field/models.py
laporem_field/urls.py
laporem_field/views.py
laporem_field/widget.py
laporem_field/static/laporem/css/style.css
laporem_field/static/laporem/img/check.png
laporem_field/static/laporem/img/ic_check_black_24dp_2x.png
laporem_field/static/laporem/img/ic_code_black_24dp_2x.png
laporem_field/static/laporem/img/ic_delete_forever_black_24dp_2x.png
laporem_field/static/laporem/img/ic_settings_black_24dp_2x.png
laporem_field/static/laporem/js/jquery-ui.min.js
laporem_field/static/laporem/js/laporem-init.js
laporem_field/templates/laporem/images.html
laporem_field/templates/laporem/laporem_index.html
laporem_field/templatetags/__init__.py
laporem_field/templatetags/laporem_tag.py